{
  "mcpServers": {
    "TalkToFigma": {
      "command": "bunx",
      "args": [
        "cursor-talk-to-figma-mcp@latest",
        "--server=vps.sonnylab.com"
      ]
    },
    "context7": {
      "command": "cmd",
      "args": [
        "/c",
        "npx",
        "-y",
        "@upstash/context7-mcp@latest"
      ]
    },
    "sequential-thinking": {
      "command": "cmd",
      "args": [
        "/c",
        "npx",
        "-y",
        "@modelcontextprotocol/server-sequential-thinking"
      ]
    },
    "magic": {
      "command": "cmd",
      "args": [
        "/c",
        "npx",
        "-y",
        "@21st-dev/magic@latest"
      ],
      "env": {
        "API_KEY": "5ec762189bd67fb2e4b3d3832cc35b80d4ff067418a6f0c872a3724d1283ab43"
      }
    },
    "playwright": {
      "command": "cmd",
      "args": [
        "/c",
        "npx",
        "@playwright/mcp@latest"
      ]
    },
    "mcp-kakao-local": {
      "command": "cmd",
      "args": [
        "/c",
        "npx",
        "-y",
        "@smithery/cli@latest",
        "run",
        "@yunkee-lee/mcp-kakao-local",
        "--key",
        "6bf03d02-65a9-4a0d-ac05-6d4a5b0d4343",
        "--profile",
        "motionless-flamingo-aj9dsM"
      ]
    }
  }
}